libertem_parallax/__init__.py
libertem_parallax/utils.py
libertem_parallax/udf/__init__.py
libertem_parallax/udf/base.py
libertem_parallax/udf/parallax.py
libertem_parallax/udf/parallax_phase_flip.py
libertem_parallax-0.1.2.dist-info/METADATA
libertem_parallax-0.1.2.dist-info/WHEEL
libertem_parallax-0.1.2.dist-info/licenses/LICENSE
libertem_parallax-0.1.2.dist-info/RECORD
