Metadata-Version: 2.4
Name: libertem-parallax
Version: 0.1.2
Summary: Parallax-based UDFs for LiberTEM
Author-email: Georgios Varnavides <gvarnavi@gmail.com>
License: Copyright (c) 2026 LiberTEM creators
License-File: LICENSE
Requires-Python: >=3.11
Requires-Dist: libertem>=0.15.2
